LICENSE
avos.py
setup.cfg
setup.py
src/AVOScript.egg-info/PKG-INFO
src/AVOScript.egg-info/SOURCES.txt
src/AVOScript.egg-info/dependency_links.txt
src/AVOScript.egg-info/entry_points.txt
src/AVOScript.egg-info/requires.txt
src/AVOScript.egg-info/top_level.txt
src/avoscript/__init__.py
src/avoscript/ast/__init__.py
src/avoscript/ast/expressions.py
src/avoscript/ast/statements.py
src/avoscript/lexer/__init__.py
src/avoscript/lexer/default.py
src/avoscript/lexer/result.py
src/avoscript/lexer/types.py
src/avoscript/parser/__init__.py
src/avoscript/parser/combinator.py